{"id": 0, "question": "萧炎第一次得知陨落心炎是哪里得知的?并且需要去哪里获得？", "answer": "68章，药老告诉他的，迦南学院 或者内院"}
{"id": 1, "question": "加列家族的请来对付萧家的“凝血散”的炼药师是谁？", "answer": "80章，炼药师柳席"}
{"id": 2, "question": "萧炎被退婚，结局是以什么样的形式收场的？", "answer": "7章，三年之约"}
{"id": 3, "question": "药老跟萧炎才相遇没多久，给了他一部强横斗技叫什么？什么品阶的？", "answer": "18章，玄阶高级斗技：八极崩"}
{"id": 4, "question": "代表迦南学院来乌坦城招生的是谁？叫什么名字呢？", "answer": "98章，若琳导师"}
{"id": 5, "question": "在萧家的成人礼上，是谁挑战了萧炎？", "answer": "41章，萧宁"}
{"id": 6, "question": "加列家族最后怎么样了？", "answer": "96章，败给萧家落魄了"}
{"id": 7, "question": "萧炎晋级斗者后，药老给他的功法是什么？", "answer": "66章，焚决"}
{"id": 8, "question": "小医仙在中州被哪方势力追杀？", "answer": "第一千零四十二章 小医仙消息 冰河谷"}
{"id": 9, "question": "萧炎的女儿叫什么名字", "answer": "第一千三百五十四章 小萧潇"}
{"id": 10, "question": "远古八族有哪些", "answer": "第一千两百九十章 古族，魂族，炎族，药族，石族，雷族以及灵族，萧族"}
{"id": 11, "question": "萧炎晋级斗尊在哪里晋级的？", "answer": "1208章"}
{"id": 12, "question": "在迦南学院萧薰儿是被谁接走的？具体的名字是？", "answer": "第五百五十五章 黑湮军副统领，翎泉"}
{"id": 13, "question": "在云岚宗的大战上，魂殿出现了一名护法抓了药老，是谁抓的？", "answer": "第六百八十四章 鹜护法"}
{"id": 14, "question": "第一次使用佛怒火莲是什么情况下创造出来的？具体是什么情况？", "answer": "第两百六十章 八翼黑蛇皇 跟它打架"}
